mawiisurv/__init__.py
mawiisurv/demo.py
mawiisurv/dnn.py
mawiisurv/func.py
mawiisurv/mawii_surv.py
mawiisurv-0.7.0.dist-info/licenses/LICENSE.txt
mawiisurv-0.7.0.dist-info/METADATA
mawiisurv-0.7.0.dist-info/WHEEL
mawiisurv-0.7.0.dist-info/top_level.txt
mawiisurv-0.7.0.dist-info/RECORD
