Metadata-Version: 2.4
Name: mawiisurv
Version: 0.7.0
Summary: Semiparametric Causal Inference for Right-Censored Outcomes with Many Weak Invalid Instruments
Author-email: Qiushi Bu <buqiushi17@mails.ucas.ac.cn>
Keywords: censored outcomes,deep neural networks,instrumental variables,generalized empirical likelihood,mendelian randomization,over-identification test,semiparametric theory,weak and invalid instruments
Classifier: License :: OSI Approved :: MIT License
Classifier: Programming Language :: Python :: 3.8
Classifier: Intended Audience :: Science/Research
Classifier: Topic :: Scientific/Engineering :: Information Analysis
Requires-Python: >=3.8
License-File: LICENSE.txt
Requires-Dist: numpy>=1.19
Requires-Dist: torch>=1.8
Requires-Dist: scipy>=1.5
Requires-Dist: scikit-learn>=0.24
Requires-Dist: xgboost>=1.3
Requires-Dist: numba>=0.53
Dynamic: license-file
